spear_ai_beamformer/__init__.py
spear_ai_beamformer/beamformer_core.py
spear_ai_beamformer/beamformer_main.py
spear_ai_beamformer/py.typed
spear_ai_beamformer-0.4.0.dist-info/METADATA
spear_ai_beamformer-0.4.0.dist-info/WHEEL
spear_ai_beamformer-0.4.0.dist-info/entry_points.txt
spear_ai_beamformer-0.4.0.dist-info/RECORD
