Metadata-Version: 2.3
Name: spear-ai-beamformer
Version: 0.4.0
Summary: A conventional beamformer
Project-URL: Changelog, https://github.com/spear-ai/beamform/tree/main/packages/beamformer/CHANGELOG.md
Project-URL: Documentation, https://github.com/spear-ai/beamform/tree/main/packages/beamformer
Project-URL: Releases, https://github.com/spear-ai/beamform/releases
Project-URL: Repository, https://github.com/spear-ai/beamform
Author-email: Spear AI <org@spear.ai>
Keywords: beamforming,processing,signal
Requires-Python: >=3.11
Requires-Dist: matplotlib<3.10,>=3.9.2
Requires-Dist: numpy<1.27,>=1.26.2
Requires-Dist: pandas<2.1,>=2.0.3
Requires-Dist: scipy<1.15,>=1.14.1
Requires-Dist: soundfile<0.13,>=0.12.1
Requires-Dist: tqdm<4.67,>=4.66.6
